{
  "usuarios": [
    {
      "id": 1,
      "username": "admin",
      "rol": "administrador",
      "password": "1234"
    },
    {
      "id": 2,
      "username": "javier",
      "rol": "mesero",
      "password": "1234"
    },
    {
      "id": 3,
      "username": "Karina",
      "password": "1234",
      "rol": "mesero"
    },
    {
      "id": 5,
      "username": "mariana",
      "rol": "mesero",
      "password": "12345"
    },
    {
      "id": 6,
      "username": "manuel",
      "rol": "mesero",
      "password": "1234"
    },
    {
      "id": 7,
      "username": "Julieth",
      "rol": "cocina",
      "password": "12345"
    },
    {
      "id": 7,
      "username": "sebas",
      "rol": "admin",
      "password": "123"
    }
  ]
}